{"info": {"author": "ravindersingh", "author_email": "ravinderkhatri@outlook.com", "bugtrack_url": null, "classifiers": ["Development Status :: 3 - Alpha", "Intended Audience :: Developers", "License :: OSI Approved :: MIT License", "Programming Language :: Python :: 3.7", "Topic :: Software Development :: Build Tools"], "description": "", "description_content_type": "", "docs_url": null, "download_url": "https://github.com/ravinderkhatri/entityinfo/archive/v01.tar.gz", "downloads": {"last_day": -1, "last_month": -1, "last_week": -1}, "home_page": "https://github.com/ravinderkhatri/entityinfo", "keywords": "EntityName,EntityInformation,RawName to Business Name,Trasactional Info", "license": "MIT", "maintainer": "", "maintainer_email": "", "name": "entityinfo", "package_url": "https://pypi.org/project/entityinfo/", "platform": "", "project_url": "https://pypi.org/project/entityinfo/", "project_urls": {"Download": "https://github.com/ravinderkhatri/entityinfo/archive/v01.tar.gz", "Homepage": "https://github.com/ravinderkhatri/entityinfo"}, "release_url": "https://pypi.org/project/entityinfo/0.1/", "requires_dist": null, "requires_python": "", "summary": "With entityinfo, you can extract information correct and full entity name", "version": "0.1", "yanked": false, "html_description": null}, "last_serial": 5544922, "releases": {"0.1": [{"comment_text": "", "digests": {"md5": "af65716c4a58a4e546b3903ce7dea504", "sha256": "008790fba11124b04c4376f01e986343962417a787ca7551e5df369e6f8dc336"}, "downloads": -1, "filename": "entityinfo-0.1.tar.gz", "has_sig": false, "md5_digest": "af65716c4a58a4e546b3903ce7dea504", "packagetype": "sdist", "python_version": "source", "requires_python": null, "size": 5856, "upload_time": "2019-07-17T09:15:04", "upload_time_iso_8601": "2019-07-17T09:15:04.030785Z", "url": "https://files.pythonhosted.org/packages/ea/94/3806ad7794165decf1950d0644635851a04253cdf778a902881886c44e5c/entityinfo-0.1.tar.gz", "yanked": false}]}, "urls": [{"comment_text": "", "digests": {"md5": "af65716c4a58a4e546b3903ce7dea504", "sha256": "008790fba11124b04c4376f01e986343962417a787ca7551e5df369e6f8dc336"}, "downloads": -1, "filename": "entityinfo-0.1.tar.gz", "has_sig": false, "md5_digest": "af65716c4a58a4e546b3903ce7dea504", "packagetype": "sdist", "python_version": "source", "requires_python": null, "size": 5856, "upload_time": "2019-07-17T09:15:04", "upload_time_iso_8601": "2019-07-17T09:15:04.030785Z", "url": "https://files.pythonhosted.org/packages/ea/94/3806ad7794165decf1950d0644635851a04253cdf778a902881886c44e5c/entityinfo-0.1.tar.gz", "yanked": false}], "timestamp": "Fri May  8 00:46:14 2020"}