{"info": {"author": "UNKNOWN", "author_email": "UNKNOWN", "bugtrack_url": null, "classifiers": [], "description": "UNKNOWN", "description_content_type": null, "docs_url": null, "download_url": "UNKNOWN", "downloads": {"last_day": -1, "last_month": -1, "last_week": -1}, "home_page": "UNKNOWN", "keywords": null, "license": "UNKNOWN", "maintainer": null, "maintainer_email": null, "name": "gitc", "package_url": "https://pypi.org/project/gitc/", "platform": "UNKNOWN", "project_url": "https://pypi.org/project/gitc/", "project_urls": {"Download": "UNKNOWN", "Homepage": "UNKNOWN"}, "release_url": "https://pypi.org/project/gitc/1.0/", "requires_dist": null, "requires_python": null, "summary": "UNKNOWN", "version": "1.0", "yanked": false, "html_description": "<div class=\"project-description\">\n            <p>UNKNOWN</p>\n\n          </div>"}, "last_serial": 2254568, "releases": {"0.1": [{"comment_text": "", "digests": {"md5": "a892f35c0e73abeb613e501521037230", "sha256": "68807589423e3ef74923d1bad52760fbb07b3e661c463768b531255eb8b05eff"}, "downloads": -1, "filename": "gitc-0.1.tar.gz", "has_sig": false, "md5_digest": "a892f35c0e73abeb613e501521037230", "packagetype": "sdist", "python_version": "source", "requires_python": null, "size": 676, "upload_time": "2016-08-01T03:42:52", "upload_time_iso_8601": "2016-08-01T03:42:52.526897Z", "url": "https://files.pythonhosted.org/packages/61/b5/9a05a7c701be7a0903be77aff00e4a585ff95ee9d42715e4d4703940eac8/gitc-0.1.tar.gz", "yanked": false}], "1.0": [{"comment_text": "", "digests": {"md5": "f510d2a74196fcb717a668938e7751a0", "sha256": "78545d61beb56829bac013c0d956bea924c861f49468205d4c370a7ed6656e8f"}, "downloads": -1, "filename": "gitc-1.0.tar.gz", "has_sig": false, "md5_digest": "f510d2a74196fcb717a668938e7751a0", "packagetype": "sdist", "python_version": "source", "requires_python": null, "size": 686, "upload_time": "2016-08-01T03:34:18", "upload_time_iso_8601": "2016-08-01T03:34:18.590221Z", "url": "https://files.pythonhosted.org/packages/ce/1a/9b12bb8523b95ebbfbd700cda3d5f3f0bd7d9e076bf7f7b27dd85a8bd269/gitc-1.0.tar.gz", "yanked": false}]}, "urls": [{"comment_text": "", "digests": {"md5": "f510d2a74196fcb717a668938e7751a0", "sha256": "78545d61beb56829bac013c0d956bea924c861f49468205d4c370a7ed6656e8f"}, "downloads": -1, "filename": "gitc-1.0.tar.gz", "has_sig": false, "md5_digest": "f510d2a74196fcb717a668938e7751a0", "packagetype": "sdist", "python_version": "source", "requires_python": null, "size": 686, "upload_time": "2016-08-01T03:34:18", "upload_time_iso_8601": "2016-08-01T03:34:18.590221Z", "url": "https://files.pythonhosted.org/packages/ce/1a/9b12bb8523b95ebbfbd700cda3d5f3f0bd7d9e076bf7f7b27dd85a8bd269/gitc-1.0.tar.gz", "yanked": false}], "timestamp": "Fri May  8 00:57:09 2020"}